{
    "elements": {
        "R20001": {
            "id": 20001,
            "type": "rectangle",
            "nodes": [
                "n20002",
                "n20003",
                "n20004",
                "n35"
            ],
            "shell_section": "floor_slab1",
            "thickness": 6,
            "load_case_names": [
                "DL",
                "LL",
                "self_weight"
            ],
            "pressures": [
                -0.02,
                -0.045,
                -0.075
            ]
        },
        "R20002": {
            "id": 20002,
            "type": "rectangle",
            "nodes": [
                "n20006",
                "n20005",
                "n20003",
                "n20002"
            ],
            "shell_section": "floor_slab1",
            "thickness": 6,
            "load_case_names": [
                "DL",
                "LL",
                "self_weight"
            ],
            "pressures": [
                -0.02,
                -0.045,
                -0.075
            ]
        },
        "R20003": {
            "id": 20003,
            "type": "rectangle",
            "nodes": [
                "n34",
                "n19004",
                "n20005",
                "n20006"
            ],
            "shell_section": "floor_slab1",
            "thickness": 6,
            "load_case_names": [
                "DL",
                "LL",
                "self_weight"
            ],
            "pressures": [
                -0.02,
                -0.045,
                -0.075
            ]
        },
        "R20004": {
            "id": 20004,
            "type": "rectangle",
            "nodes": [
                "n20003",
                "n20009",
                "n20010",
                "n20004"
            ],
            "shell_section": "floor_slab1",
            "thickness": 6,
            "load_case_names": [
                "DL",
                "LL",
                "self_weight"
            ],
            "pressures": [
                -0.02,
                -0.045,
                -0.075
            ]
        },
        "R20005": {
            "id": 20005,
            "type": "rectangle",
            "nodes": [
                "n20005",
                "n20011",
                "n20009",
                "n20003"
            ],
            "shell_section": "floor_slab1",
            "thickness": 6,
            "load_case_names": [
                "DL",
                "LL",
                "self_weight"
            ],
            "pressures": [
                -0.02,
                -0.045,
                -0.075
            ]
        },
        "R20006": {
            "id": 20006,
            "type": "rectangle",
            "nodes": [
                "n19004",
                "n19010",
                "n20011",
                "n20005"
            ],
            "shell_section": "floor_slab1",
            "thickness": 6,
            "load_case_names": [
                "DL",
                "LL",
                "self_weight"
            ],
            "pressures": [
                -0.02,
                -0.045,
                -0.075
            ]
        },
        "R20007": {
            "id": 20007,
            "type": "rectangle",
            "nodes": [
                "n20009",
                "n20013",
                "n39",
                "n20010"
            ],
            "shell_section": "floor_slab1",
            "thickness": 6,
            "load_case_names": [
                "DL",
                "LL",
                "self_weight"
            ],
            "pressures": [
                -0.02,
                -0.045,
                -0.075
            ]
        },
        "R20008": {
            "id": 20008,
            "type": "rectangle",
            "nodes": [
                "n20011",
                "n20015",
                "n20013",
                "n20009"
            ],
            "shell_section": "floor_slab1",
            "thickness": 6,
            "load_case_names": [
                "DL",
                "LL",
                "self_weight"
            ],
            "pressures": [
                -0.02,
                -0.045,
                -0.075
            ]
        },
        "R20009": {
            "id": 20009,
            "type": "rectangle",
            "nodes": [
                "n19010",
                "n38",
                "n20015",
                "n20011"
            ],
            "shell_section": "floor_slab1",
            "thickness": 6,
            "load_case_names": [
                "DL",
                "LL",
                "self_weight"
            ],
            "pressures": [
                -0.02,
                -0.045,
                -0.075
            ]
        }
    }
}