{
  "center_of_mass": [
    14.982758620689657,
    16.56896551724138
  ],
  "center_of_rigidity": [
    16.166667049728883,
    16.166667528555426
  ],
  "total_stiffness_matrix": [
    [
      1009538.8988355729,
      0.0,
      1.4918608570724246e-09
    ],
    [
      0.0,
      2271459.2594666774,
      -1.1751589923392203e-08
    ],
    [
      1.4918608570724246e-09,
      -1.1751589923392203e-08,
      376677638.88484716
    ]
  ],
  "element_details": [
    {
      "name": "cz3",
      "Kxx": 0.6525826723249483,
      "Kyy": 0.6525826723249483,
      "Kxy": 0.0,
      "x": 0.0,
      "y": 0.0,
      "rotation": 0.0
    },
    {
      "name": "cz6",
      "Kxx": 84128.02404207362,
      "Kyy": 189288.05409466565,
      "Kxy": 0.0,
      "x": 10.0,
      "y": 0.0,
      "rotation": 0.0
    },
    {
      "name": "cz9",
      "Kxx": 84128.02404207362,
      "Kyy": 189288.05409466565,
      "Kxy": 0.0,
      "x": 22.0,
      "y": 0.0,
      "rotation": 0.0
    },
    {
      "name": "cz12",
      "Kxx": 0.6525826723249483,
      "Kyy": 0.6525826723249483,
      "Kxy": 0.0,
      "x": 33.0,
      "y": 0.0,
      "rotation": 0.0
    },
    {
      "name": "cz15",
      "Kxx": 84128.02404207362,
      "Kyy": 189288.05409466565,
      "Kxy": 0.0,
      "x": 0.0,
      "y": 10.0,
      "rotation": 0.0
    },
    {
      "name": "cz18",
      "Kxx": 84128.02404207362,
      "Kyy": 189288.05409466565,
      "Kxy": 0.0,
      "x": 10.0,
      "y": 10.0,
      "rotation": 0.0
    },
    {
      "name": "cz21",
      "Kxx": 84128.02404207362,
      "Kyy": 189288.05409466565,
      "Kxy": 0.0,
      "x": 22.0,
      "y": 10.0,
      "rotation": 0.0
    },
    {
      "name": "cz24",
      "Kxx": 84128.02404207362,
      "Kyy": 189288.05409466565,
      "Kxy": 0.0,
      "x": 33.0,
      "y": 10.0,
      "rotation": 0.0
    },
    {
      "name": "cz27",
      "Kxx": 84128.02404207362,
      "Kyy": 189288.05409466565,
      "Kxy": 0.0,
      "x": 0.0,
      "y": 22.0,
      "rotation": 0.0
    },
    {
      "name": "cz30",
      "Kxx": 84128.02404207362,
      "Kyy": 189288.05409466565,
      "Kxy": 0.0,
      "x": 10.0,
      "y": 22.0,
      "rotation": 0.0
    },
    {
      "name": "cz33",
      "Kxx": 84128.02404207362,
      "Kyy": 189288.05409466565,
      "Kxy": 0.0,
      "x": 22.0,
      "y": 22.0,
      "rotation": 0.0
    },
    {
      "name": "cz36",
      "Kxx": 84128.02404207362,
      "Kyy": 189288.05409466565,
      "Kxy": 0.0,
      "x": 33.0,
      "y": 22.0,
      "rotation": 0.0
    },
    {
      "name": "cz39",
      "Kxx": 0.6525826723249483,
      "Kyy": 0.6525826723249483,
      "Kxy": 0.0,
      "x": 0.0,
      "y": 33.0,
      "rotation": 0.0
    },
    {
      "name": "cz42",
      "Kxx": 84128.02404207362,
      "Kyy": 189288.05409466565,
      "Kxy": 0.0,
      "x": 10.0,
      "y": 33.0,
      "rotation": 0.0
    },
    {
      "name": "cz45",
      "Kxx": 84128.02404207362,
      "Kyy": 189288.05409466565,
      "Kxy": 0.0,
      "x": 22.0,
      "y": 33.0,
      "rotation": 0.0
    },
    {
      "name": "cz48",
      "Kxx": 0.6525826723249483,
      "Kyy": 0.6525826723249483,
      "Kxy": 0.0,
      "x": 33.0,
      "y": 33.0,
      "rotation": 0.0
    }
  ],
  "eccentricity": [
    -1.183908429039226,
    0.40229798868595523
  ],
  "eccentricity_total": [
    -2.8339084290392265,
    2.0522979886859556
  ],
  "torsional_moment_applied": 431.9424731917337,
  "torsional_rigidity_Jr_total": 376677638.88484716,
  "shear_distribution": [
    {
      "name": "cz3",
      "Fx": 7.673961622401416e-05,
      "Fy": 1.0885774424472524e-05,
      "Fx_direct_trans": 6.464165700575315e-05,
      "Fy_direct_trans": 2.2983733284414536e-05,
      "Fx_coupling_trans": 0.0,
      "Fy_coupling_trans": 0.0,
      "Fx_torsion": 1.2097959218261003e-05,
      "Fy_torsion": -1.2097958859942012e-05,
      "Fx_trans": 6.464165700575315e-05,
      "Fy_trans": 2.2983733284414536e-05,
      "dx_from_cor": -16.166667049728883,
      "dy_from_cor": -16.166667528555426,
      "Kxx": 0.6525826723249483,
      "Kyy": 0.6525826723249483,
      "Kxy": 0.0,
      "x": 0.0,
      "y": 0.0,
      "rotation": 0.0
    },
    {
      "name": "cz6",
      "Fx": 9.892926294951755,
      "Fy": 5.328123861051084,
      "Fx_direct_trans": 8.333311786114331,
      "Fy_direct_trans": 6.666659005422239,
      "Fx_coupling_trans": 0.0,
      "Fy_coupling_trans": 0.0,
      "Fx_torsion": 1.5596145088374243,
      "Fy_torsion": -1.338535144371154,
      "Fx_trans": 8.333311786114331,
      "Fy_trans": 6.666659005422239,
      "dx_from_cor": -6.166667049728883,
      "dy_from_cor": -16.166667528555426,
      "Kxx": 84128.02404207362,
      "Kyy": 189288.05409466565,
      "Kxy": 0.0,
      "x": 10.0,
      "y": 0.0,
      "rotation": 0.0
    },
    {
      "name": "cz9",
      "Fx": 9.892926294951755,
      "Fy": 7.9328407369459875,
      "Fx_direct_trans": 8.333311786114331,
      "Fy_direct_trans": 6.666659005422239,
      "Fx_coupling_trans": 0.0,
      "Fy_coupling_trans": 0.0,
      "Fx_torsion": 1.5596145088374243,
      "Fy_torsion": 1.2661817315237482,
      "Fx_trans": 8.333311786114331,
      "Fy_trans": 6.666659005422239,
      "dx_from_cor": 5.833332950271117,
      "dy_from_cor": -16.166667528555426,
      "Kxx": 84128.02404207362,
      "Kyy": 189288.05409466565,
      "Kxy": 0.0,
      "x": 22.0,
      "y": 0.0,
      "rotation": 0.0
    },
    {
      "name": "cz12",
      "Fx": 7.673961622401416e-05,
      "Fy": 3.5580576460664734e-05,
      "Fx_direct_trans": 6.464165700575315e-05,
      "Fy_direct_trans": 2.2983733284414536e-05,
      "Fx_coupling_trans": 0.0,
      "Fy_coupling_trans": 0.0,
      "Fx_torsion": 1.2097959218261003e-05,
      "Fy_torsion": 1.2596843176250201e-05,
      "Fx_trans": 6.464165700575315e-05,
      "Fy_trans": 2.2983733284414536e-05,
      "dx_from_cor": 16.833332950271117,
      "dy_from_cor": -16.166667528555426,
      "Kxx": 0.6525826723249483,
      "Kyy": 0.6525826723249483,
      "Kxy": 0.0,
      "x": 33.0,
      "y": 0.0,
      "rotation": 0.0
    },
    {
      "name": "cz15",
      "Fx": 8.928216340916606,
      "Fy": 3.1575264644719994,
      "Fx_direct_trans": 8.333311786114331,
      "Fy_direct_trans": 6.666659005422239,
      "Fx_coupling_trans": 0.0,
      "Fy_coupling_trans": 0.0,
      "Fx_torsion": 0.5949045548022751,
      "Fy_torsion": -3.5091325409502394,
      "Fx_trans": 8.333311786114331,
      "Fy_trans": 6.666659005422239,
      "dx_from_cor": -16.166667049728883,
      "dy_from_cor": -6.1666675285554255,
      "Kxx": 84128.02404207362,
      "Kyy": 189288.05409466565,
      "Kxy": 0.0,
      "x": 0.0,
      "y": 10.0,
      "rotation": 0.0
    },
    {
      "name": "cz18",
      "Fx": 8.928216340916606,
      "Fy": 5.328123861051084,
      "Fx_direct_trans": 8.333311786114331,
      "Fy_direct_trans": 6.666659005422239,
      "Fx_coupling_trans": 0.0,
      "Fy_coupling_trans": 0.0,
      "Fx_torsion": 0.5949045548022751,
      "Fy_torsion": -1.338535144371154,
      "Fx_trans": 8.333311786114331,
      "Fy_trans": 6.666659005422239,
      "dx_from_cor": -6.166667049728883,
      "dy_from_cor": -6.1666675285554255,
      "Kxx": 84128.02404207362,
      "Kyy": 189288.05409466565,
      "Kxy": 0.0,
      "x": 10.0,
      "y": 10.0,
      "rotation": 0.0
    },
    {
      "name": "cz21",
      "Fx": 8.928216340916606,
      "Fy": 7.9328407369459875,
      "Fx_direct_trans": 8.333311786114331,
      "Fy_direct_trans": 6.666659005422239,
      "Fx_coupling_trans": 0.0,
      "Fy_coupling_trans": 0.0,
      "Fx_torsion": 0.5949045548022751,
      "Fy_torsion": 1.2661817315237482,
      "Fx_trans": 8.333311786114331,
      "Fy_trans": 6.666659005422239,
      "dx_from_cor": 5.833332950271117,
      "dy_from_cor": -6.1666675285554255,
      "Kxx": 84128.02404207362,
      "Kyy": 189288.05409466565,
      "Kxy": 0.0,
      "x": 22.0,
      "y": 10.0,
      "rotation": 0.0
    },
    {
      "name": "cz24",
      "Fx": 8.928216340916606,
      "Fy": 10.32049787318298,
      "Fx_direct_trans": 8.333311786114331,
      "Fy_direct_trans": 6.666659005422239,
      "Fx_coupling_trans": 0.0,
      "Fy_coupling_trans": 0.0,
      "Fx_torsion": 0.5949045548022751,
      "Fy_torsion": 3.653838867760742,
      "Fx_trans": 8.333311786114331,
      "Fy_trans": 6.666659005422239,
      "dx_from_cor": 16.833332950271117,
      "dy_from_cor": -6.1666675285554255,
      "Kxx": 84128.02404207362,
      "Kyy": 189288.05409466565,
      "Kxy": 0.0,
      "x": 33.0,
      "y": 10.0,
      "rotation": 0.0
    },
    {
      "name": "cz27",
      "Fx": 7.770564396074428,
      "Fy": 3.1575264644719994,
      "Fx_direct_trans": 8.333311786114331,
      "Fy_direct_trans": 6.666659005422239,
      "Fx_coupling_trans": 0.0,
      "Fy_coupling_trans": 0.0,
      "Fx_torsion": -0.5627473900399037,
      "Fy_torsion": -3.5091325409502394,
      "Fx_trans": 8.333311786114331,
      "Fy_trans": 6.666659005422239,
      "dx_from_cor": -16.166667049728883,
      "dy_from_cor": 5.8333324714445745,
      "Kxx": 84128.02404207362,
      "Kyy": 189288.05409466565,
      "Kxy": 0.0,
      "x": 0.0,
      "y": 22.0,
      "rotation": 0.0
    },
    {
      "name": "cz30",
      "Fx": 7.770564396074428,
      "Fy": 5.328123861051084,
      "Fx_direct_trans": 8.333311786114331,
      "Fy_direct_trans": 6.666659005422239,
      "Fx_coupling_trans": 0.0,
      "Fy_coupling_trans": 0.0,
      "Fx_torsion": -0.5627473900399037,
      "Fy_torsion": -1.338535144371154,
      "Fx_trans": 8.333311786114331,
      "Fy_trans": 6.666659005422239,
      "dx_from_cor": -6.166667049728883,
      "dy_from_cor": 5.8333324714445745,
      "Kxx": 84128.02404207362,
      "Kyy": 189288.05409466565,
      "Kxy": 0.0,
      "x": 10.0,
      "y": 22.0,
      "rotation": 0.0
    },
    {
      "name": "cz33",
      "Fx": 7.770564396074428,
      "Fy": 7.9328407369459875,
      "Fx_direct_trans": 8.333311786114331,
      "Fy_direct_trans": 6.666659005422239,
      "Fx_coupling_trans": 0.0,
      "Fy_coupling_trans": 0.0,
      "Fx_torsion": -0.5627473900399037,
      "Fy_torsion": 1.2661817315237482,
      "Fx_trans": 8.333311786114331,
      "Fy_trans": 6.666659005422239,
      "dx_from_cor": 5.833332950271117,
      "dy_from_cor": 5.8333324714445745,
      "Kxx": 84128.02404207362,
      "Kyy": 189288.05409466565,
      "Kxy": 0.0,
      "x": 22.0,
      "y": 22.0,
      "rotation": 0.0
    },
    {
      "name": "cz36",
      "Fx": 7.770564396074428,
      "Fy": 10.32049787318298,
      "Fx_direct_trans": 8.333311786114331,
      "Fy_direct_trans": 6.666659005422239,
      "Fx_coupling_trans": 0.0,
      "Fy_coupling_trans": 0.0,
      "Fx_torsion": -0.5627473900399037,
      "Fy_torsion": 3.653838867760742,
      "Fx_trans": 8.333311786114331,
      "Fy_trans": 6.666659005422239,
      "dx_from_cor": 16.833332950271117,
      "dy_from_cor": 5.8333324714445745,
      "Kxx": 84128.02404207362,
      "Kyy": 189288.05409466565,
      "Kxy": 0.0,
      "x": 33.0,
      "y": 22.0,
      "rotation": 0.0
    },
    {
      "name": "cz39",
      "Fx": 5.2044814187821945e-05,
      "Fy": 1.0885774424472524e-05,
      "Fx_direct_trans": 6.464165700575315e-05,
      "Fy_direct_trans": 2.2983733284414536e-05,
      "Fx_coupling_trans": 0.0,
      "Fy_coupling_trans": 0.0,
      "Fx_torsion": -1.2596842817931212e-05,
      "Fy_torsion": -1.2097958859942012e-05,
      "Fx_trans": 6.464165700575315e-05,
      "Fy_trans": 2.2983733284414536e-05,
      "dx_from_cor": -16.166667049728883,
      "dy_from_cor": 16.833332471444574,
      "Kxx": 0.6525826723249483,
      "Kyy": 0.6525826723249483,
      "Kxy": 0.0,
      "x": 0.0,
      "y": 33.0,
      "rotation": 0.0
    },
    {
      "name": "cz42",
      "Fx": 6.709383446635764,
      "Fy": 5.328123861051084,
      "Fx_direct_trans": 8.333311786114331,
      "Fy_direct_trans": 6.666659005422239,
      "Fx_coupling_trans": 0.0,
      "Fy_coupling_trans": 0.0,
      "Fx_torsion": -1.6239283394785677,
      "Fy_torsion": -1.338535144371154,
      "Fx_trans": 8.333311786114331,
      "Fy_trans": 6.666659005422239,
      "dx_from_cor": -6.166667049728883,
      "dy_from_cor": 16.833332471444574,
      "Kxx": 84128.02404207362,
      "Kyy": 189288.05409466565,
      "Kxy": 0.0,
      "x": 10.0,
      "y": 33.0,
      "rotation": 0.0
    },
    {
      "name": "cz45",
      "Fx": 6.709383446635764,
      "Fy": 7.9328407369459875,
      "Fx_direct_trans": 8.333311786114331,
      "Fy_direct_trans": 6.666659005422239,
      "Fx_coupling_trans": 0.0,
      "Fy_coupling_trans": 0.0,
      "Fx_torsion": -1.6239283394785677,
      "Fy_torsion": 1.2661817315237482,
      "Fx_trans": 8.333311786114331,
      "Fy_trans": 6.666659005422239,
      "dx_from_cor": 5.833332950271117,
      "dy_from_cor": 16.833332471444574,
      "Kxx": 84128.02404207362,
      "Kyy": 189288.05409466565,
      "Kxy": 0.0,
      "x": 22.0,
      "y": 33.0,
      "rotation": 0.0
    },
    {
      "name": "cz48",
      "Fx": 5.2044814187821945e-05,
      "Fy": 3.5580576460664734e-05,
      "Fx_direct_trans": 6.464165700575315e-05,
      "Fy_direct_trans": 2.2983733284414536e-05,
      "Fx_coupling_trans": 0.0,
      "Fy_coupling_trans": 0.0,
      "Fx_torsion": -1.2596842817931212e-05,
      "Fy_torsion": 1.2596843176250201e-05,
      "Fx_trans": 6.464165700575315e-05,
      "Fy_trans": 2.2983733284414536e-05,
      "dx_from_cor": 16.833332950271117,
      "dy_from_cor": 16.833332471444574,
      "Kxx": 0.6525826723249483,
      "Kyy": 0.6525826723249483,
      "Kxy": 0.0,
      "x": 33.0,
      "y": 33.0,
      "rotation": 0.0
    }
  ],
  "total_shear_distributed": [
    100.0,
    80.00000000000003
  ],
  "displacements": [
    9.905512320064385e-05,
    3.521964995259631e-05,
    1.1467165252243222e-06
  ],
  "load_combination": "mass",
  "z_level": "22.0",
  "Lx": 33.0,
  "Ly": 33.0,
  "Vx_total": 100,
  "Vy_total": 80
}