{
    "n30013": [
        "n30013",
        "self_weight",
        0.0,
        0.0,
        -0.55,
        0.0,
        0.0,
        0.0
    ],
    "n32003": [
        "n32003",
        "self_weight",
        0.0,
        0.0,
        -1.0999999999999996,
        0.0,
        0.0,
        0.0
    ],
    "n32004": [
        "n32004",
        "self_weight",
        0.0,
        0.0,
        -0.5499999999999998,
        0.0,
        0.0,
        0.0
    ],
    "n59": [
        "n59",
        "self_weight",
        0.0,
        0.0,
        -0.275,
        0.0,
        0.0,
        0.0
    ],
    "n30015": [
        "n30015",
        "self_weight",
        0.0,
        0.0,
        -0.55,
        0.0,
        0.0,
        0.0
    ],
    "n32005": [
        "n32005",
        "self_weight",
        0.0,
        0.0,
        -1.0999999999999996,
        0.0,
        0.0,
        0.0
    ],
    "n58": [
        "n58",
        "self_weight",
        0.0,
        0.0,
        -0.275,
        0.0,
        0.0,
        0.0
    ],
    "n31004": [
        "n31004",
        "self_weight",
        0.0,
        0.0,
        -0.5499999999999998,
        0.0,
        0.0,
        0.0
    ],
    "n32009": [
        "n32009",
        "self_weight",
        0.0,
        0.0,
        -1.0999999999999996,
        0.0,
        0.0,
        0.0
    ],
    "n32010": [
        "n32010",
        "self_weight",
        0.0,
        0.0,
        -0.5499999999999998,
        0.0,
        0.0,
        0.0
    ],
    "n32011": [
        "n32011",
        "self_weight",
        0.0,
        0.0,
        -1.0999999999999996,
        0.0,
        0.0,
        0.0
    ],
    "n31010": [
        "n31010",
        "self_weight",
        0.0,
        0.0,
        -0.5499999999999998,
        0.0,
        0.0,
        0.0
    ],
    "n32013": [
        "n32013",
        "self_weight",
        0.0,
        0.0,
        -0.55,
        0.0,
        0.0,
        0.0
    ],
    "n63": [
        "n63",
        "self_weight",
        0.0,
        0.0,
        -0.275,
        0.0,
        0.0,
        0.0
    ],
    "n32015": [
        "n32015",
        "self_weight",
        0.0,
        0.0,
        -0.55,
        0.0,
        0.0,
        0.0
    ],
    "n62": [
        "n62",
        "self_weight",
        0.0,
        0.0,
        -0.275,
        0.0,
        0.0,
        0.0
    ]
}